README.md
setup.py
drf_jsonresponse/__init__.py
drf_jsonresponse/mixins.py
drf_jsonresponse/pagination.py
drf_jsonresponse.egg-info/PKG-INFO
drf_jsonresponse.egg-info/SOURCES.txt
drf_jsonresponse.egg-info/dependency_links.txt
drf_jsonresponse.egg-info/not-zip-safe
drf_jsonresponse.egg-info/requires.txt
drf_jsonresponse.egg-info/top_level.txt