Metadata-Version: 2.1
Name: drf-jsonresponse
Version: 0.2
Summary: DRF modifies mixins to return a custom jsonresponse
Home-page: http://github.com/tongling/clinicaltrial
Author: RunningFaster
Author-email: Vladimir1993rj@gmail.com
License: MIT
Platform: any
